{
  "name": "custom-scroll",
  "version": "0.6.5",
  "title": "Customize your scrollbar",
  "author": {
    "name" : "Mostovoy Andrey",
    "email" : "mostovoyav@gmail.com",
    "url" : "https://github.com/standy/"
  },
  "main": [
    "jquery.custom-scroll.js"
  ],
  "dependencies": {
    "jquery": ">=1.7"
  },
  "homepage": "https://github.com/standy/custom-scroll",
  "demo": "http://standy.github.io/custom-scroll",
  "download": "https://raw.githubusercontent.com/standy/custom-scroll/master/jquery.custom-scroll.js",

  "description": "Customize your scrollbar",
  "keywords": [
	  "scrollbar",
      "native scrollbar",
	  "customize",
	  "custom-scroll"
  ],
  "licenses": [
    {
      "type": "MIT",
      "url": "https://raw.githubusercontent.com/standy/custom-scroll/master/LICENSE"
    }
  ]
}
